mindroom/__init__.py
mindroom/agent_prompts.py
mindroom/agents.py
mindroom/ai.py
mindroom/background_tasks.py
mindroom/bot.py
mindroom/cli.py
mindroom/commands.py
mindroom/config.py
mindroom/config_commands.py
mindroom/config_confirmation.py
mindroom/constants.py
mindroom/credentials.py
mindroom/credentials_sync.py
mindroom/error_handling.py
mindroom/file_watcher.py
mindroom/interactive.py
mindroom/logging_config.py
mindroom/py.typed
mindroom/response_tracker.py
mindroom/room_cleanup.py
mindroom/routing.py
mindroom/scheduling.py
mindroom/stop.py
mindroom/streaming.py
mindroom/teams.py
mindroom/thread_utils.py
mindroom/tools_metadata.json
mindroom/tools_metadata.py
mindroom/topic_generator.py
mindroom/voice_handler.py
mindroom/api/__init__.py
mindroom/api/credentials.py
mindroom/api/google_integration.py
mindroom/api/google_tools_helper.py
mindroom/api/homeassistant_integration.py
mindroom/api/integrations.py
mindroom/api/main.py
mindroom/api/matrix_operations.py
mindroom/api/tools.py
mindroom/custom_tools/__init__.py
mindroom/custom_tools/config_manager.py
mindroom/custom_tools/gmail.py
mindroom/custom_tools/google_calendar.py
mindroom/custom_tools/google_sheets.py
mindroom/custom_tools/homeassistant.py
mindroom/matrix/__init__.py
mindroom/matrix/client.py
mindroom/matrix/event_info.py
mindroom/matrix/identity.py
mindroom/matrix/large_messages.py
mindroom/matrix/mentions.py
mindroom/matrix/message_builder.py
mindroom/matrix/message_content.py
mindroom/matrix/presence.py
mindroom/matrix/rooms.py
mindroom/matrix/state.py
mindroom/matrix/typing.py
mindroom/matrix/users.py
mindroom/memory/__init__.py
mindroom/memory/config.py
mindroom/memory/functions.py
mindroom/tools/__init__.py
mindroom/tools/agentql.py
mindroom/tools/airflow.py
mindroom/tools/apify.py
mindroom/tools/arxiv.py
mindroom/tools/aws_lambda.py
mindroom/tools/aws_ses.py
mindroom/tools/baidusearch.py
mindroom/tools/brightdata.py
mindroom/tools/browserbase.py
mindroom/tools/cal_com.py
mindroom-0.1.3.dist-info/METADATA
mindroom-0.1.3.dist-info/WHEEL
mindroom-0.1.3.dist-info/entry_points.txt
mindroom-0.1.3.dist-info/RECORD
