Metadata-Version: 2.4
Name: mindroom
Version: 0.1.3
Summary: A universal interface for AI agents with persistent memory, where every conversation has a home
Project-URL: documentation, https://github.com/mindroom-ai/mindroom
Project-URL: homepage, https://github.com/mindroom-ai/mindroom
Project-URL: repository, https://github.com/mindroom-ai/mindroom
Author: mindroom team
Classifier: Programming Language :: Python :: 3 :: Only
Classifier: Programming Language :: Python :: 3.12
Classifier: Programming Language :: Python :: 3.13
Requires-Python: >=3.12
Requires-Dist: agentql
Requires-Dist: agno[anthropic,google,ollama,openai]>=1.7.6
Requires-Dist: aiofiles
Requires-Dist: aiohttp
Requires-Dist: apify-client>=1.12.2; platform_machine != 'aarch64'
Requires-Dist: arxiv
Requires-Dist: atlassian-python-api
Requires-Dist: baidusearch
Requires-Dist: beautifulsoup4
Requires-Dist: boto3>=1.40.8
Requires-Dist: browserbase
Requires-Dist: cartesia
Requires-Dist: cerebras-cloud-sdk>=1.46
Requires-Dist: chromadb>=1.0.15
Requires-Dist: composio-agno
Requires-Dist: crawl4ai>=0.7.3
Requires-Dist: cron-descriptor>=1.4.5
Requires-Dist: croniter>=6
Requires-Dist: daytona
Requires-Dist: ddgs
Requires-Dist: diskcache>=5.6.3
Requires-Dist: docker
Requires-Dist: duckdb
Requires-Dist: e2b-code-interpreter
Requires-Dist: elevenlabs
Requires-Dist: exa-py
Requires-Dist: fal-client
Requires-Dist: fastapi[standard]>=0.116.1
Requires-Dist: firecrawl-py<3
Requires-Dist: google-api-python-client>=2.178
Requires-Dist: google-auth-httplib2>=0.2
Requires-Dist: google-auth-oauthlib>=1.2.2
Requires-Dist: google-auth>=2.40.3
Requires-Dist: google-cloud-bigquery
Requires-Dist: google-genai
Requires-Dist: google-maps-places
Requires-Dist: google-search-results>=2.4.2
Requires-Dist: googlemaps
Requires-Dist: googlesearch-python
Requires-Dist: groq>=0.31
Requires-Dist: httpx>=0.27
Requires-Dist: humanize>=4.12.3
Requires-Dist: jira>=3.10.5
Requires-Dist: linkup-sdk>=0.2.8
Requires-Dist: loguru>=0.7.3
Requires-Dist: lumaai
Requires-Dist: lxml-html-clean
Requires-Dist: markdown>=3.7
Requires-Dist: matrix-nio>=0.24
Requires-Dist: mcp[cli]>=1.12.4
Requires-Dist: mem0ai>=0.1.115
Requires-Dist: moviepy
Requires-Dist: newspaper4k
Requires-Dist: openai
Requires-Dist: oxylabs
Requires-Dist: pandas>=2.2
Requires-Dist: playwright
Requires-Dist: praw
Requires-Dist: psycopg-binary
Requires-Dist: py-trello
Requires-Dist: pycountry
Requires-Dist: pydantic>=2
Requires-Dist: pygithub>=2.5
Requires-Dist: pyjwt>=2.8
Requires-Dist: pypdf
Requires-Dist: python-dotenv>=1
Requires-Dist: pytz
Requires-Dist: pyyaml>=6
Requires-Dist: replicate>=1.0.7
Requires-Dist: requests
Requires-Dist: resend
Requires-Dist: rich
Requires-Dist: scrapegraph-py
Requires-Dist: slack-sdk
Requires-Dist: spider-client
Requires-Dist: spotipy>=2.25.1
Requires-Dist: sqlalchemy
Requires-Dist: streamlit
Requires-Dist: structlog>=24.1
Requires-Dist: supabase>=2.18.1
Requires-Dist: tavily-python
Requires-Dist: tenacity>=9.1.2
Requires-Dist: todoist-api-python
Requires-Dist: tweepy
Requires-Dist: twilio
Requires-Dist: typer>=0.16
Requires-Dist: uvicorn>=0.35
Requires-Dist: watchdog>=6
Requires-Dist: webexpythonsdk
Requires-Dist: wikipedia
Requires-Dist: yfinance
Requires-Dist: youtube-transcript-api
Requires-Dist: zep-cloud>=3.3
